pygocomma/__init__.py
pygocomma/asyncio_udp.py
pygocomma/const.py
pygocomma/r9.py
pygocomma-1.12.dist-info/LICENSE
pygocomma-1.12.dist-info/METADATA
pygocomma-1.12.dist-info/WHEEL
pygocomma-1.12.dist-info/top_level.txt
pygocomma-1.12.dist-info/RECORD
