Metadata-Version: 2.1
Name: pygocomma
Version: 1.12
Summary: Asyncio module for Gocomma R9 devices control
Home-page: https://github.com/p3g4asus/pygocomma
Author: p3g4asus
Author-email: fulminedipegasus@gmail.com
License: UNKNOWN
Platform: UNKNOWN
Classifier: Programming Language :: Python :: 3
Classifier: License :: OSI Approved :: MIT License
Classifier: Operating System :: OS Independent
Requires-Dist: pycryptodome
